cli_imagefetcher/__init__.py
cli_imagefetcher/cli.py
cli_imagefetcher/CONSTANTS.py
cli_imagefetcher/imageManipulation.py
cli_imagefetcher/order.py
cli_imagefetcher/search.py
cli_imagefetcher/validation.py
cli_imagefetcher-0.5.0.dist-info/entry_points.txt
cli_imagefetcher-0.5.0.dist-info/WHEEL
cli_imagefetcher-0.5.0.dist-info/METADATA
cli_imagefetcher-0.5.0.dist-info/RECORD
