Metadata-Version: 2.1
Name: cli-imagefetcher
Version: 0.5.0
Summary: Search for and order products from an EO API
Author: Alan Scandrett
Author-email: alanscandrett@gmail.com
Requires-Python: >=3.10,<4.0
Classifier: Programming Language :: Python :: 3
Classifier: Programming Language :: Python :: 3.10
Requires-Dist: requests (>=2.28.1,<3.0.0)
Requires-Dist: typer (>=0.5.0,<0.6.0)
